utils_base/Hash.py
utils_base/Parallel.py
utils_base/__init__.py
utils_base/console/Console.py
utils_base/console/Log.py
utils_base/console/__init__.py
utils_base/console/constants/COLOR_BACKGROUND.py
utils_base/console/constants/COLOR_FOREGROUND.py
utils_base/console/constants/COLOR_FORMAT.py
utils_base/console/constants/LEVEL_TO_STYLE.py
utils_base/console/constants/__init__.py
utils_base/ds/Chunker.py
utils_base/ds/Dict.py
utils_base/ds/Format.py
utils_base/ds/Iter.py
utils_base/ds/List.py
utils_base/ds/Parse.py
utils_base/ds/String.py
utils_base/ds/__init__.py
utils_base/file/BigJSONFile.py
utils_base/file/CSVFile.py
utils_base/file/File.py
utils_base/file/FileOrDirectory.py
utils_base/file/JSONFile.py
utils_base/file/Markdown.py
utils_base/file/TSVFile.py
utils_base/file/XSVFile.py
utils_base/file/__init__.py
utils_base/file/pdf_file/PDFFile.py
utils_base/file/pdf_file/PDFFileCompressMixin.py
utils_base/file/pdf_file/PDFTextMixin.py
utils_base/file/pdf_file/__init__.py
utils_base/geo/LatLng.py
utils_base/geo/LatLngLK.py
utils_base/geo/__init__.py
utils_base/image/Image.py
utils_base/image/__init__.py
utils_base/time/Time.py
utils_base/time/TimeDelta.py
utils_base/time/TimeFormat.py
utils_base/time/TimeUnit.py
utils_base/time/TimeZoneOffset.py
utils_base/time/__init__.py
utils_base/xml/XMLElement.py
utils_base/xml/XMLUtils.py
utils_base/xml/_.py
utils_base/xml/__init__.py
utils_base_nuuuwan-1.1.1.dist-info/licenses/LICENSE
utils_base_nuuuwan-1.1.1.dist-info/METADATA
utils_base_nuuuwan-1.1.1.dist-info/WHEEL
utils_base_nuuuwan-1.1.1.dist-info/top_level.txt
utils_base_nuuuwan-1.1.1.dist-info/RECORD
